diolib.py
diosh.py
parametrizedDeco.py
pydiodon.py
pydiodon-0.1.0.data/data/share/pydiodon/CoA_LMF82.txt
pydiodon-0.1.0.data/data/share/pydiodon/ade4_doubs_env.txt
pydiodon-0.1.0.data/data/share/pydiodon/ade4_doubs_fish.txt
pydiodon-0.1.0.data/data/share/pydiodon/diatoms_sweden.txt
pydiodon-0.1.0.data/data/share/pydiodon/gallery.yaml
pydiodon-0.1.0.data/data/share/pydiodon/gallery.yap
pydiodon-0.1.0.data/data/share/pydiodon/guiana_trees.sw.dis
pydiodon-0.1.0.data/data/share/pydiodon/laurales.sw.dis
pydiodon-0.1.0.dist-info/licenses/AUTHORS
pydiodon-0.1.0.dist-info/licenses/LICENCE
pydiodon-0.1.0.dist-info/METADATA
pydiodon-0.1.0.dist-info/WHEEL
pydiodon-0.1.0.dist-info/entry_points.txt
pydiodon-0.1.0.dist-info/top_level.txt
pydiodon-0.1.0.dist-info/RECORD
