Metadata-Version: 2.4
Name: pydiodon
Version: 0.1.0
Summary: numpy library for linear dimension reduction
Home-page: https://gitlab.inria.fr/diodon/pydiodon
Author: Alain Franc
Author-email: Alain Franc <alain.franc@inrae.fr>
Project-URL: Homepage, https://gitlab.inria.fr/diodon/pydiodon
License-File: LICENCE
License-File: AUTHORS
Requires-Dist: PyQt5
Requires-Dist: numpy
Requires-Dist: scipy
Requires-Dist: matplotlib
Requires-Dist: h5py
Requires-Dist: prompt_toolkit
Requires-Dist: pyyaml
Requires-Dist: print_color
Dynamic: license-file
